kinto_elasticsearch/__init__.py
kinto_elasticsearch/command_reindex.py
kinto_elasticsearch/indexer.py
kinto_elasticsearch/listener.py
kinto_elasticsearch/views.py
kinto_elasticsearch-0.3.1.dist-info/DESCRIPTION.rst
kinto_elasticsearch-0.3.1.dist-info/METADATA
kinto_elasticsearch-0.3.1.dist-info/RECORD
kinto_elasticsearch-0.3.1.dist-info/WHEEL
kinto_elasticsearch-0.3.1.dist-info/entry_points.txt
kinto_elasticsearch-0.3.1.dist-info/metadata.json
kinto_elasticsearch-0.3.1.dist-info/top_level.txt
