Metadata-Version: 2.0
Name: kinto-elasticsearch
Version: 0.3.1
Summary: Index and search records using ElasticSearch.
Home-page: https://github.com/kinto/kinto-elasticsearch
Author: Mozilla Services
Author-email: services-dev@mozilla.com
License: Apache License (2.0)
Keywords: kinto elasticsearch index
Platform: UNKNOWN
Classifier: Development Status :: 2 - Pre-Alpha
Classifier: Intended Audience :: Developers
Classifier: License :: OSI Approved :: Apache Software License
Classifier: Natural Language :: English
Classifier: Programming Language :: Python :: 3
Classifier: Programming Language :: Python :: 3.3
Classifier: Programming Language :: Python :: 3.4
Classifier: Programming Language :: Python :: 3.5
Requires-Dist: elasticsearch
Requires-Dist: kinto (>=6.0.0)
